pepper_cli.py
pepper_cli-0.2.0.dist-info/LICENSE
pepper_cli-0.2.0.dist-info/METADATA
pepper_cli-0.2.0.dist-info/WHEEL
pepper_cli-0.2.0.dist-info/entry_points.txt
pepper_cli-0.2.0.dist-info/RECORD
