Metadata-Version: 2.1
Name: pepper-cli
Version: 0.2.0
Summary: Get information about any PEP (Python Enhancement Proposal)
License: MIT
Author: Noah Tanner
Author-email: 50159154+kevinshome@users.noreply.github.com
Requires-Python: >=3.8,<4.0
Classifier: License :: OSI Approved :: MIT License
Classifier: Programming Language :: Python :: 3
Classifier: Programming Language :: Python :: 3.8
Classifier: Programming Language :: Python :: 3.9
Classifier: Programming Language :: Python :: 3.10
Classifier: Programming Language :: Python :: 3.11
Provides-Extra: dev
Provides-Extra: offline
Provides-Extra: webview
Requires-Dist: black ; extra == "dev"
Requires-Dist: bottle ; extra == "offline"
Requires-Dist: pywebview ; extra == "webview"
